skland-0.0.1.dist-info/METADATA
skland-0.0.1.dist-info/WHEEL
skland/__init__.py
skland-0.0.1.dist-info/RECORD
