Metadata-Version: 2.1
Name: skland
Version: 0.0.1
Summary: 森空岛Python请求库
Author-Email: djkcyl <cyl@cyllive.cn>
License: MIT
Requires-Python: >=3.8
